Metadata-Version: 2.1
Name: music-fsl
Version: 0.1.3
Summary: Few-shot learning for music instrument recognition using PyTorch
Home-page: https://blog.godatadriven.com/setup-py
Author: Hugo Flores García
Author-email: hugofloresgarcia@u.northwestern.edu
License-File: LICENSE
